MANIFEST.in
README.rst
setup.py
docs/HISTORY.txt
docs/LICENSE.GPL
docs/LICENSE.txt
ftw/__init__.py
ftw.recipe.checkversions.egg-info/PKG-INFO
ftw.recipe.checkversions.egg-info/SOURCES.txt
ftw.recipe.checkversions.egg-info/dependency_links.txt
ftw.recipe.checkversions.egg-info/entry_points.txt
ftw.recipe.checkversions.egg-info/namespace_packages.txt
ftw.recipe.checkversions.egg-info/not-zip-safe
ftw.recipe.checkversions.egg-info/requires.txt
ftw.recipe.checkversions.egg-info/top_level.txt
ftw/recipe/__init__.py
ftw/recipe/checkversions/__init__.py
ftw/recipe/checkversions/buildout.py
ftw/recipe/checkversions/checker.py
ftw/recipe/checkversions/command.py
ftw/recipe/checkversions/progresslogger.py
ftw/recipe/checkversions/pypi.py
ftw/recipe/checkversions/recipe.py
ftw/recipe/checkversions/testing.py
ftw/recipe/checkversions/utils.py
ftw/recipe/checkversions/tests/__init__.py
ftw/recipe/checkversions/tests/fshelpers.py
ftw/recipe/checkversions/tests/test_buildout.py
ftw/recipe/checkversions/tests/test_checker.py
ftw/recipe/checkversions/tests/test_command.py
ftw/recipe/checkversions/tests/test_progresslogger.py
ftw/recipe/checkversions/tests/test_pypi.py
ftw/recipe/checkversions/tests/test_recipe.py
ftw/recipe/checkversions/tests/test_utils.py