Metadata-Version: 1.0
Name: ftw.recipe.checkversions
Version: 1.0.0
Summary: Buildout recipe for finding new package versions.
Home-page: https://github.com/4teamwork/ftw.recipe.checkversions
Author: 4teamwork AG
Author-email: mailto:info@4teamwork.ch
License: GPL2
Keywords: ftw recipe checkversions buildout
Platform: UNKNOWN
Classifier: Intended Audience :: Developers
Classifier: Topic :: Software Development :: Libraries :: Python Modules
